mpesakit/__init__.py
mpesakit/errors.py
mpesakit/mpesa_client.py
mpesakit/account_balance/__init__.py
mpesakit/account_balance/account_balance.py
mpesakit/account_balance/schemas.py
mpesakit/auth/__init__.py
mpesakit/auth/access_token.py
mpesakit/auth/token_manager.py
mpesakit/b2b_express_checkout/__init__.py
mpesakit/b2b_express_checkout/b2b_express_checkout.py
mpesakit/b2b_express_checkout/schemas.py
mpesakit/b2c/__init__.py
mpesakit/b2c/b2c.py
mpesakit/b2c/schemas.py
mpesakit/b2c_account_top_up/__init__.py
mpesakit/b2c_account_top_up/b2c_account_top_up.py
mpesakit/b2c_account_top_up/schemas.py
mpesakit/bill_manager/__init__.py
mpesakit/bill_manager/bill_manager.py
mpesakit/bill_manager/schemas.py
mpesakit/business_buy_goods/__init__.py
mpesakit/business_buy_goods/business_buy_goods.py
mpesakit/business_buy_goods/schemas.py
mpesakit/business_paybill/__init__.py
mpesakit/business_paybill/business_paybill.py
mpesakit/business_paybill/schemas.py
mpesakit/c2b/__init__.py
mpesakit/c2b/c2b.py
mpesakit/c2b/schemas.py
mpesakit/dynamic_qr_code/__init__.py
mpesakit/dynamic_qr_code/dynamic_qr_code.py
mpesakit/dynamic_qr_code/schemas.py
mpesakit/http_client/__init__.py
mpesakit/http_client/http_client.py
mpesakit/http_client/mpesa_async_http_client.py
mpesakit/http_client/mpesa_http_client.py
mpesakit/mpesa_express/__init__.py
mpesakit/mpesa_express/schemas.py
mpesakit/mpesa_express/stk_push.py
mpesakit/mpesa_ratiba/__init__.py
mpesakit/mpesa_ratiba/mpesa_ratiba.py
mpesakit/mpesa_ratiba/schemas.py
mpesakit/reversal/__init__.py
mpesakit/reversal/reversal.py
mpesakit/reversal/schemas.py
mpesakit/security/__init__.py
mpesakit/security/get_credential.py
mpesakit/security/ip_whitelist.py
mpesakit/security/certs/ProductionCertificate.cer
mpesakit/security/certs/SandboxCertificate.cer
mpesakit/services/__init__.py
mpesakit/services/b2b.py
mpesakit/services/b2c.py
mpesakit/services/balance.py
mpesakit/services/bill.py
mpesakit/services/c2b.py
mpesakit/services/dynamic_qr.py
mpesakit-2.1.0.dist-info/METADATA
mpesakit-2.1.0.dist-info/WHEEL
mpesakit-2.1.0.dist-info/licenses/AUTHORS.md
mpesakit-2.1.0.dist-info/licenses/LICENSE
mpesakit-2.1.0.dist-info/RECORD
