Metadata-Version: 2.4
Name: mpesakit
Version: 2.1.0
Summary: A Python SDK for integrating with M-Pesa APIs
Project-URL: Homepage, https://github.com/Byte-Barn/mpesakit
Project-URL: Issues, https://github.com/Byte-Barn/mpesakit/issues
Project-URL: Repository, https://github.com/Byte-Barn/mpesakit
Author-email: John Kagunda <johnmkagunda@gmail.com>
Maintainer-email: John Kagunda <johnmkagunda@gmail.com>
License: APACHE-2.0
License-File: AUTHORS.md
License-File: LICENSE
Keywords: africa,api,django,fastapi,flask,mobile money,mpesa,payment,payments,rest,sdk
Classifier: Development Status :: 4 - Beta
Classifier: Intended Audience :: Developers
Classifier: License :: OSI Approved :: Apache Software License
Classifier: Operating System :: OS Independent
Classifier: Programming Language :: Python :: 3.10
Classifier: Programming Language :: Python :: 3.11
Classifier: Programming Language :: Python :: 3.12
Classifier: Topic :: Internet :: WWW/HTTP :: Dynamic Content
Classifier: Topic :: Software Development :: Libraries :: Python Modules
Classifier: Typing :: Typed
Requires-Python: >=3.10
Requires-Dist: cryptography>=41.0.7
Requires-Dist: httpx<1.0.0,>=0.27.0
Requires-Dist: pydantic<3.0.0,>=2.10.6
Requires-Dist: pydantic[email]<3.0.0,>=2.10.6
Requires-Dist: requests<3.0.0,>=2.32.5
Requires-Dist: tenacity<10.0.0,>=9.1.2
Requires-Dist: typing-extensions<5.0.0,>=4.12.2
Provides-Extra: dev
Requires-Dist: bandit; extra == 'dev'
Requires-Dist: build; extra == 'dev'
Requires-Dist: coverage; extra == 'dev'
Requires-Dist: hatch; extra == 'dev'
Requires-Dist: hatch-vcs; extra == 'dev'
Requires-Dist: hatchling; extra == 'dev'
Requires-Dist: mypy; extra == 'dev'
Requires-Dist: pytest; extra == 'dev'
Requires-Dist: pytest-asyncio<1.0.0,>=0.23.6; extra == 'dev'
Requires-Dist: pytest-cov; extra == 'dev'
Requires-Dist: ruff; extra == 'dev'
Requires-Dist: types-requests; extra == 'dev'
Provides-Extra: test
Requires-Dist: bandit; extra == 'test'
Requires-Dist: mypy; extra == 'test'
Requires-Dist: pyngrok; extra == 'test'
Requires-Dist: pytest; extra == 'test'
Requires-Dist: pytest-asyncio<1.0.0,>=0.23.6; extra == 'test'
Requires-Dist: pytest-cov; extra == 'test'
Requires-Dist: types-requests; extra == 'test'
